bindit/__init__.py
bindit/cli.py
bindit/docker.py
bindit/partial.py
bindit/shell.py
bindit-0.2.2.dist-info/AUTHORS.rst
bindit-0.2.2.dist-info/LICENSE
bindit-0.2.2.dist-info/METADATA
bindit-0.2.2.dist-info/WHEEL
bindit-0.2.2.dist-info/entry_points.txt
bindit-0.2.2.dist-info/top_level.txt
bindit-0.2.2.dist-info/RECORD
