Metadata-Version: 2.1
Name: bindit
Version: 0.2.2
Summary: Takes the drudgery out of bind-mounting volumes on Docker and Singularity
Home-page: https://github.com/jooh/bindit
Author: Johan Carlin
Author-email: johan.carlin@gmail.com
License: MIT license
Keywords: bindit
Platform: UNKNOWN
Classifier: Development Status :: 2 - Pre-Alpha
Classifier: Intended Audience :: Developers
Classifier: License :: OSI Approved :: MIT License
Classifier: Natural Language :: English
Classifier: Programming Language :: Python :: 3.4
Classifier: Programming Language :: Python :: 3.5
Classifier: Programming Language :: Python :: 3.6
Classifier: Programming Language :: Python :: 3.7
Requires-Dist: Click (>=6.0)
